pyrdio/__init__.py
pyrdio-1.1.2.dist-info/DESCRIPTION.rst
pyrdio-1.1.2.dist-info/METADATA
pyrdio-1.1.2.dist-info/metadata.json
pyrdio-1.1.2.dist-info/pbr.json
pyrdio-1.1.2.dist-info/RECORD
pyrdio-1.1.2.dist-info/top_level.txt
pyrdio-1.1.2.dist-info/WHEEL
