Metadata-Version: 2.0
Name: pyrdio
Version: 1.1.2
Summary: A simple Python wrapper for Rdio's API
Home-page: https://github.com/rcrdclub/pyrdio
Author: Hery Ratsimihah
Author-email: UNKNOWN
License: MIT
Keywords: rdio library
Platform: UNKNOWN
Classifier: Development Status :: 4 - Beta
Classifier: Intended Audience :: Developers
Classifier: Natural Language :: English
Classifier: License :: OSI Approved :: MIT License
Classifier: Programming Language :: Python :: 2.7
Requires-Dist: oauth2
